{
  "filename": "2020-01-24_10:56:44-\u5c0f\u94bb\u98ce\u7684\u5e7f\u64ad.md",
  "title": "\u5c0f\u94bb\u98ce\u7684\u5e7f\u64ad",
  "author": "[\u5c0f\u94bb\u98ce\uff08\u6765\u81ea\u8c46\u74e3\uff09",
  "author_url": "https://www.douban.com/people/58982367/",
  "source": "\u5e7f\u64ad",
  "source_url": "https://www.douban.com/people/58982367/)",
  "long_date": "2020-01-24_10:56:44",
  "content": "\n\n\u6b66\u6c49\u5c01\u57ce.day01\n\n\n\n\n\n\n\n\n\n",
  "pics": [
    {
      "name": "./pic/2020-01-24_10:56:44-\u5c0f\u94bb\u98ce\u7684\u5e7f\u64ad1.jpg)  ",
      "url": "./pic/2020-01-24_10:56:44-\u5c0f\u94bb\u98ce\u7684\u5e7f\u64ad1.jpg)  "
    },
    {
      "name": "./pic/2020-01-24_10:56:44-\u5c0f\u94bb\u98ce\u7684\u5e7f\u64ad2.jpg)  ",
      "url": "./pic/2020-01-24_10:56:44-\u5c0f\u94bb\u98ce\u7684\u5e7f\u64ad2.jpg)  "
    },
    {
      "name": "./pic/2020-01-24_10:56:44-\u5c0f\u94bb\u98ce\u7684\u5e7f\u64ad3.jpg)  ",
      "url": "./pic/2020-01-24_10:56:44-\u5c0f\u94bb\u98ce\u7684\u5e7f\u64ad3.jpg)  "
    },
    {
      "name": "./pic/2020-01-24_10:56:44-\u5c0f\u94bb\u98ce\u7684\u5e7f\u64ad4.jpg)  ",
      "url": "./pic/2020-01-24_10:56:44-\u5c0f\u94bb\u98ce\u7684\u5e7f\u64ad4.jpg)  "
    },
    {
      "name": "./pic/2020-01-24_10:56:44-\u5c0f\u94bb\u98ce\u7684\u5e7f\u64ad5.jpg)  ",
      "url": "./pic/2020-01-24_10:56:44-\u5c0f\u94bb\u98ce\u7684\u5e7f\u64ad5.jpg)  "
    },
    {
      "name": "./pic/2020-01-24_10:56:44-\u5c0f\u94bb\u98ce\u7684\u5e7f\u64ad6.jpg)  ",
      "url": "./pic/2020-01-24_10:56:44-\u5c0f\u94bb\u98ce\u7684\u5e7f\u64ad6.jpg)  "
    },
    {
      "name": "./pic/2020-01-24_10:56:44-\u5c0f\u94bb\u98ce\u7684\u5e7f\u64ad7.jpg)  ",
      "url": "./pic/2020-01-24_10:56:44-\u5c0f\u94bb\u98ce\u7684\u5e7f\u64ad7.jpg)  "
    },
    {
      "name": "./pic/2020-01-24_10:56:44-\u5c0f\u94bb\u98ce\u7684\u5e7f\u64ad8.jpg)  ",
      "url": "./pic/2020-01-24_10:56:44-\u5c0f\u94bb\u98ce\u7684\u5e7f\u64ad8.jpg)  "
    },
    {
      "name": "./pic/2020-01-24_10:56:44-\u5c0f\u94bb\u98ce\u7684\u5e7f\u64ad9.jpg)  ",
      "url": "./pic/2020-01-24_10:56:44-\u5c0f\u94bb\u98ce\u7684\u5e7f\u64ad9.jpg)  "
    }
  ]
}