{
  "filename": "2020-01-27_12:55:50-\u72d0\u68ee\u7684\u5e7f\u64ad.md",
  "title": "\u72d0\u68ee\u7684\u5e7f\u64ad",
  "author": "[\u72d0\u68ee\uff08\u6765\u81ea\u8c46\u74e3\uff09",
  "author_url": "https://www.douban.com/people/153795705/",
  "source": "\u5e7f\u64ad",
  "source_url": "https://www.douban.com/people/153795705/status/2775710119/)",
  "long_date": "2020-01-27_12:55:50",
  "content": "\n\n\u5199\u4e2a\u65e5\u8bb0\u800c\u5df2\n\u90fd\u53d1\u5e03\u4e0d\u51fa\u6765\n&#35;\u5fc3\u7d2f&#35;\n\n",
  "pics": [
    {
      "name": "./pic/2020-01-27_12:55:50-\u72d0\u68ee\u7684\u5e7f\u64ad1.jpg)  ",
      "url": "./pic/2020-01-27_12:55:50-\u72d0\u68ee\u7684\u5e7f\u64ad1.jpg)  "
    }
  ]
}