{
  "filename": "2020-02-19_23:04:36-\u8c4c\u8c46\u7684\u5e7f\u64ad.md",
  "title": "\u8c4c\u8c46\u7684\u5e7f\u64ad",
  "author": "[\u8c4c\u8c46\uff08\u6765\u81ea\u8c46\u74e3\uff09",
  "author_url": "https://www.douban.com/people/wondersays/",
  "source": "\u5e7f\u64ad",
  "source_url": "https://www.douban.com/people/wondersays/status/2821600753/)",
  "long_date": "2020-02-19_23:04:36",
  "content": "\n\n\u73b0\u5728\u53ea\u80fd\u901a\u8fc7\u793e\u533a\u4e70\u4e1c\u897f\u4e86\u3002\u6240\u4ee5\u4f5c\u4e3a\u4e00\u4e2a\u5357\u65b9\u4eba\uff0c\u751f\u5e73\u7b2c\u4e00\u6b21\uff0c\u56e2\u8d2d\u4e8650\u65a4\u9762\u7c89\u3002\u8be5\u5546\u5bb6\u53ea\u6709\u8fd9\u4e00\u4e2a\u89c4\u683c\u3002\n",
  "pics": []
}