{
  "filename": "2020-02-11_13:08:40-\u66c9\u5b87\u7684\u5e7f\u64ad.md",
  "title": "\u66c9\u5b87\u7684\u5e7f\u64ad",
  "author": "[\u66c9\u5b87\uff08\u6765\u81ea\u8c46\u74e3\uff09",
  "author_url": "https://www.douban.com/people/30338291/",
  "source": "\u5e7f\u64ad",
  "source_url": "https://www.douban.com/people/30338291/status/2804023731/)",
  "long_date": "2020-02-11_13:08:40",
  "content": "\n\n\u4e00\u76f4\u90fd\u662f99%\u7684\u6211\u4eec\uff0c\u5728\u8fd9\u4e2a\u65f6\u5019\u6210\u4e86\u90a31%\u3002\n",
  "pics": []
}