{
  "filename": "2020-01-27_10:47:33-\u767e\u76cf\u7684\u5e7f\u64ad.md",
  "title": "\u767e\u76cf\u7684\u5e7f\u64ad",
  "author": "[\u767e\u76cf\uff08\u6765\u81ea\u8c46\u74e3\uff09",
  "author_url": "https://www.douban.com/people/hongshulin/",
  "source": "\u5e7f\u64ad",
  "source_url": "https://www.douban.com/people/hongshulin/status/2775568426/)",
  "long_date": "2020-01-27_10:47:33",
  "content": "\n\n\u533b\u7597\u884c\u4e1a\u53ea\u662f\u4e00\u4e2a\u88ab\u9053\u5fb7\u7ed1\u67b6\u4e86\u7684\u666e\u901a\u793e\u755c\u804c\u4e1a\uff0c\u4ece\u533b\u4eba\u5458\u53ea\u662f\u8017\u6750\u3002\n",
  "pics": []
}