{
  "filename": "2020-02-12_22:41:54-\u6c99\u4e18\u7684\u5e7f\u64ad.md",
  "title": "\u6c99\u4e18\u7684\u5e7f\u64ad",
  "author": "[\u6c99\u4e18\uff08\u6765\u81ea\u8c46\u74e3\uff09",
  "author_url": "https://www.douban.com/people/54876686/",
  "source": "\u5e7f\u64ad",
  "source_url": "https://www.douban.com/people/54876686/status/2807165025/)",
  "long_date": "2020-02-12_22:41:54",
  "content": "\n\n\u767e\u6b65\u4ead\uff0c\u767e\u6b65\u4ead\uff0c\u767e\u6b65\u4ead\u3002\u8fde\u7eed\u5220\u4e86\u4e24\u6b21\uff0c\u6211\u770b\u80fd\u4e0d\u80fd\u53d1\u51fa\u6765\u3002\n\n",
  "pics": [
    {
      "name": "./pic/2020-02-12_22:41:54-\u6c99\u4e18\u7684\u5e7f\u64ad1.jpg)  ",
      "url": "./pic/2020-02-12_22:41:54-\u6c99\u4e18\u7684\u5e7f\u64ad1.jpg)  "
    }
  ]
}